return_result/__init__.py
return_result/result.py
return_result-1.1.0.dist-info/WHEEL
return_result-1.1.0.dist-info/METADATA
return_result-1.1.0.dist-info/RECORD
