Metadata-Version: 2.1
Name: return-result
Version: 1.1.0
Summary: This defines a decorator that causes the 'result' variable to be returned when there is no explicit return
Home-page: https://github.com/bolunthompson/return-result
Keywords: return result,result variable,nim result
Author: Bolun Thompson
Author-email: abolunthompson@gmail.com
Requires-Python: >=3.6,<4.0
Classifier: Development Status :: 5 - Production/Stable
Classifier: Intended Audience :: Developers
Classifier: Programming Language :: Python :: 3
Classifier: Programming Language :: Python :: 3.6
Classifier: Programming Language :: Python :: 3.7
Classifier: Programming Language :: Python :: 3.8
Classifier: Typing :: Typed
